{"product_uid": 100007, "product_description": "The Quantum Adjustable 2-Light LED Black Emergency Lighting Unit from Lithonia Lighting provides a minimum of 90 minutes of illumination upon loss of power. Adjust the direction of light using the unique track-and-swivel design of the 2 heads. This unit is ideal for applications requiring attractive equipment with quick installation.Advanced LED technology is dependable and energy efficient2 adjustable heads allow you to direct light where it is neededEngineering-grade thermoplastic housing is impact-resistant, scratch-resistant and corrosion-proofIntegrated LEDs means no bulbs are requiredTypical life of the LEDs is 10 years of maintenance-free operationBlack housing has a compact low-profile designSealed, maintenance-free Ni-cad battery delivers 90 minute capacity to the LEDsDual voltage input capability (120 to 277-volt)Easily installs to wall or ceilingUL damp-location listed", "product_attributes": {"Battery Power Type": "Ni-Cad", "Battery Size": ".Built-In", "Bulb Type Included": "LED", "Bullet01": "Advanced LED technology is dependable and energy efficient", "Bullet02": "2 adjustable heads allow you to direct light where it is needed", "Bullet03": "Engineering-grade thermoplastic housing is impact-resistant, scratch-resistant and corrosion-proof", "Bullet04": "Integrated LEDs means no bulbs are required", "Bullet05": "Typical life of the LEDs is 10 years of maintenance-free operation", "Bullet06": "Black housing has a compact low-profile design", "Bullet07": "Sealed, maintenance-free Ni-cad battery delivers 90 minute capacity to the LEDs", "Bullet08": "Dual voltage input capability (120 to 277-volt)", "Bullet09": "Easily installs to wall or ceiling", "Bullet10": "UL damp-location listed", "Certifications and Listings": "1-UL Listed,OSHA Compliant", "Commercial Light Type": "Exit and Emergency", "Connection Type": "Hardwired", "Emergency run time (min.)": "90", "ENERGY STAR Certified": "No", "Fixture Color/Finish": "Black", "Fixture Color/Finish Family": "Black", "Lamp heads": "Yes", "Light Source": "LED", "Material": "Plastic", "Maximum Wattage (watts)": "0", "MFG Brand Name": "Lithonia Lighting", "Number of Bulbs Required": "0", "Product Depth (in.)": "2.75", "Product Height (in.)": "4.25", "Product Weight (lb.)": "1.5", "Product Width (in.)": "10.25"}}